[
  {
    "no": 1,
    "name": "パワーピアス",
    "gold": 2500,
    "effect_id": 0,
    "bonus": {
      "str": 25,
      "int": 0,
      "dex": 0,
      "vit": 0,
      "agi": 0,
      "mnd": 0,
      "lck": 0,
      "lp": 0
    },
    "attrib": 0,
    "spare1": 0,
    "spare2": 0
  },
  {
    "no": 2,
    "name": "パワーリング",
    "gold": 50000,
    "effect_id": 0,
    "bonus": {
      "str": 50,
      "int": 0,
      "dex": 0,
      "vit": 0,
      "agi": 0,
      "mnd": 0,
      "lck": 0,
      "lp": 0
    },
    "attrib": 0,
    "spare1": 0,
    "spare2": 0
  },
  {
    "no": 3,
    "name": "パワーリスト",
    "gold": 999999,
    "effect_id": 0,
    "bonus": {
      "str": 100,
      "int": 0,
      "dex": 0,
      "vit": 0,
      "agi": 0,
      "mnd": 0,
      "lck": 0,
      "lp": 0
    },
    "attrib": 0,
    "spare1": 0,
    "spare2": 0
  },
  {
    "no": 4,
    "name": "マジックピアス",
    "gold": 2500,
    "effect_id": 0,
    "bonus": {
      "str": 0,
      "int": 25,
      "dex": 0,
      "vit": 0,
      "agi": 0,
      "mnd": 0,
      "lck": 0,
      "lp": 0
    },
    "attrib": 0,
    "spare1": 0,
    "spare2": 0
  },
  {
    "no": 5,
    "name": "マジックリング",
    "gold": 50000,
    "effect_id": 0,
    "bonus": {
      "str": 0,
      "int": 50,
      "dex": 0,
      "vit": 0,
      "agi": 0,
      "mnd": 0,
      "lck": 0,
      "lp": 0
    },
    "attrib": 0,
    "spare1": 0,
    "spare2": 0
  },
  {
    "no": 6,
    "name": "サークレット",
    "gold": 999999,
    "effect_id": 0,
    "bonus": {
      "str": 0,
      "int": 100,
      "dex": 0,
      "vit": 0,
      "agi": 0,
      "mnd": 0,
      "lck": 0,
      "lp": 0
    },
    "attrib": 0,
    "spare1": 0,
    "spare2": 0
  },
  {
    "no": 7,
    "name": "クロスピアス",
    "gold": 2500,
    "effect_id": 0,
    "bonus": {
      "str": 0,
      "int": 0,
      "dex": 25,
      "vit": 0,
      "agi": 0,
      "mnd": 0,
      "lck": 0,
      "lp": 0
    },
    "attrib": 0,
    "spare1": 0,
    "spare2": 0
  },
  {
    "no": 8,
    "name": "クロスリング",
    "gold": 50000,
    "effect_id": 0,
    "bonus": {
      "str": 0,
      "int": 0,
      "dex": 50,
      "vit": 0,
      "agi": 0,
      "mnd": 0,
      "lck": 0,
      "lp": 0
    },
    "attrib": 0,
    "spare1": 0,
    "spare2": 0
  },
  {
    "no": 9,
    "name": "神秘の指輪",
    "gold": 999999,
    "effect_id": 0,
    "bonus": {
      "str": 0,
      "int": 0,
      "dex": 100,
      "vit": 0,
      "agi": 0,
      "mnd": 0,
      "lck": 0,
      "lp": 0
    },
    "attrib": 0,
    "spare1": 0,
    "spare2": 0
  },
  {
    "no": 10,
    "name": "ライフピアス",
    "gold": 2500,
    "effect_id": 0,
    "bonus": {
      "str": 0,
      "int": 0,
      "dex": 0,
      "vit": 25,
      "agi": 0,
      "mnd": 0,
      "lck": 0,
      "lp": 0
    },
    "attrib": 0,
    "spare1": 0,
    "spare2": 0
  },
  {
    "no": 11,
    "name": "ライフリング",
    "gold": 50000,
    "effect_id": 0,
    "bonus": {
      "str": 0,
      "int": 0,
      "dex": 0,
      "vit": 50,
      "agi": 0,
      "mnd": 0,
      "lck": 0,
      "lp": 0
    },
    "attrib": 0,
    "spare1": 0,
    "spare2": 0
  },
  {
    "no": 12,
    "name": "命の指輪",
    "gold": 999999,
    "effect_id": 0,
    "bonus": {
      "str": 0,
      "int": 0,
      "dex": 0,
      "vit": 100,
      "agi": 0,
      "mnd": 0,
      "lck": 0,
      "lp": 0
    },
    "attrib": 0,
    "spare1": 0,
    "spare2": 0
  },
  {
    "no": 13,
    "name": "スピードピアス",
    "gold": 2500,
    "effect_id": 0,
    "bonus": {
      "str": 0,
      "int": 0,
      "dex": 0,
      "vit": 0,
      "agi": 0,
      "mnd": 25,
      "lck": 0,
      "lp": 0
    },
    "attrib": 0,
    "spare1": 0,
    "spare2": 0
  },
  {
    "no": 14,
    "name": "スピードリング",
    "gold": 50000,
    "effect_id": 0,
    "bonus": {
      "str": 0,
      "int": 0,
      "dex": 0,
      "vit": 0,
      "agi": 0,
      "mnd": 50,
      "lck": 0,
      "lp": 0
    },
    "attrib": 0,
    "spare1": 0,
    "spare2": 0
  },
  {
    "no": 15,
    "name": "エルメスの靴",
    "gold": 999999,
    "effect_id": 0,
    "bonus": {
      "str": 0,
      "int": 0,
      "dex": 0,
      "vit": 0,
      "agi": 0,
      "mnd": 100,
      "lck": 0,
      "lp": 0
    },
    "attrib": 0,
    "spare1": 0,
    "spare2": 0
  },
  {
    "no": 16,
    "name": "スキルピアス",
    "gold": 2500,
    "effect_id": 0,
    "bonus": {
      "str": 0,
      "int": 0,
      "dex": 0,
      "vit": 0,
      "agi": 25,
      "mnd": 0,
      "lck": 0,
      "lp": 0
    },
    "attrib": 0,
    "spare1": 0,
    "spare2": 0
  },
  {
    "no": 17,
    "name": "スキルリング",
    "gold": 50000,
    "effect_id": 0,
    "bonus": {
      "str": 0,
      "int": 0,
      "dex": 0,
      "vit": 0,
      "agi": 50,
      "mnd": 0,
      "lck": 0,
      "lp": 0
    },
    "attrib": 0,
    "spare1": 0,
    "spare2": 0
  },
  {
    "no": 18,
    "name": "ピッキングリング",
    "gold": 999999,
    "effect_id": 0,
    "bonus": {
      "str": 0,
      "int": 0,
      "dex": 0,
      "vit": 0,
      "agi": 100,
      "mnd": 0,
      "lck": 0,
      "lp": 0
    },
    "attrib": 0,
    "spare1": 0,
    "spare2": 0
  },
  {
    "no": 19,
    "name": "富豪の紋章",
    "gold": 2500,
    "effect_id": 0,
    "bonus": {
      "str": 0,
      "int": 0,
      "dex": 0,
      "vit": 0,
      "agi": 0,
      "mnd": 0,
      "lck": 25,
      "lp": 0
    },
    "attrib": 0,
    "spare1": 0,
    "spare2": 0
  },
  {
    "no": 20,
    "name": "貴族の紋章",
    "gold": 50000,
    "effect_id": 0,
    "bonus": {
      "str": 0,
      "int": 0,
      "dex": 0,
      "vit": 0,
      "agi": 0,
      "mnd": 0,
      "lck": 50,
      "lp": 0
    },
    "attrib": 0,
    "spare1": 0,
    "spare2": 0
  },
  {
    "no": 21,
    "name": "王家の紋章",
    "gold": 999999,
    "effect_id": 0,
    "bonus": {
      "str": 0,
      "int": 0,
      "dex": 0,
      "vit": 0,
      "agi": 0,
      "mnd": 0,
      "lck": 100,
      "lp": 0
    },
    "attrib": 0,
    "spare1": 0,
    "spare2": 0
  },
  {
    "no": 22,
    "name": "ラックピアス",
    "gold": 2500,
    "effect_id": 0,
    "bonus": {
      "str": 0,
      "int": 0,
      "dex": 0,
      "vit": 0,
      "agi": 0,
      "mnd": 0,
      "lck": 0,
      "lp": 25
    },
    "attrib": 0,
    "spare1": 0,
    "spare2": 0
  },
  {
    "no": 23,
    "name": "ラックリング",
    "gold": 50000,
    "effect_id": 0,
    "bonus": {
      "str": 0,
      "int": 0,
      "dex": 0,
      "vit": 0,
      "agi": 0,
      "mnd": 0,
      "lck": 0,
      "lp": 50
    },
    "attrib": 0,
    "spare1": 0,
    "spare2": 0
  },
  {
    "no": 24,
    "name": "幸せの指輪",
    "gold": 999999,
    "effect_id": 0,
    "bonus": {
      "str": 0,
      "int": 0,
      "dex": 0,
      "vit": 0,
      "agi": 0,
      "mnd": 0,
      "lck": 0,
      "lp": 100
    },
    "attrib": 0,
    "spare1": 0,
    "spare2": 0
  },
  {
    "no": 25,
    "name": "近視眼鏡",
    "gold": 15000,
    "effect_id": 0,
    "bonus": {
      "str": 0,
      "int": 0,
      "dex": 0,
      "vit": 0,
      "agi": 0,
      "mnd": 0,
      "lck": 0,
      "lp": 0
    },
    "attrib": 10,
    "spare1": 0,
    "spare2": 0
  },
  {
    "no": 26,
    "name": "赤外線スコープ",
    "gold": 75000,
    "effect_id": 0,
    "bonus": {
      "str": 0,
      "int": 0,
      "dex": 0,
      "vit": 0,
      "agi": 0,
      "mnd": 0,
      "lck": 0,
      "lp": 0
    },
    "attrib": 20,
    "spare1": 0,
    "spare2": 0
  },
  {
    "no": 27,
    "name": "デジタルスコープ",
    "gold": 8000000,
    "effect_id": 0,
    "bonus": {
      "str": 0,
      "int": 0,
      "dex": 0,
      "vit": 0,
      "agi": 0,
      "mnd": 0,
      "lck": 0,
      "lp": 0
    },
    "attrib": 30,
    "spare1": 0,
    "spare2": 0
  },
  {
    "no": 28,
    "name": "蝶の羽",
    "gold": 15000,
    "effect_id": 0,
    "bonus": {
      "str": 0,
      "int": 0,
      "dex": 0,
      "vit": 0,
      "agi": 0,
      "mnd": 0,
      "lck": 0,
      "lp": 0
    },
    "attrib": 0,
    "spare1": 10,
    "spare2": 0
  },
  {
    "no": 29,
    "name": "翼竜の翼",
    "gold": 75000,
    "effect_id": 0,
    "bonus": {
      "str": 0,
      "int": 0,
      "dex": 0,
      "vit": 0,
      "agi": 0,
      "mnd": 0,
      "lck": 0,
      "lp": 0
    },
    "attrib": 0,
    "spare1": 20,
    "spare2": 0
  },
  {
    "no": 30,
    "name": "飛竜の翼",
    "gold": 8000000,
    "effect_id": 0,
    "bonus": {
      "str": 0,
      "int": 0,
      "dex": 0,
      "vit": 0,
      "agi": 0,
      "mnd": 0,
      "lck": 0,
      "lp": 0
    },
    "attrib": 0,
    "spare1": 30,
    "spare2": 0
  },
  {
    "no": 31,
    "name": "必殺の魂",
    "gold": 75000,
    "effect_id": 0,
    "bonus": {
      "str": 0,
      "int": 0,
      "dex": 0,
      "vit": 0,
      "agi": 0,
      "mnd": 0,
      "lck": 0,
      "lp": 0
    },
    "attrib": 0,
    "spare1": 0,
    "spare2": 10
  },
  {
    "no": 32,
    "name": "鬼武者の魂",
    "gold": 8000000,
    "effect_id": 0,
    "bonus": {
      "str": 0,
      "int": 0,
      "dex": 0,
      "vit": 0,
      "agi": 0,
      "mnd": 0,
      "lck": 0,
      "lp": 0
    },
    "attrib": 0,
    "spare1": 0,
    "spare2": 20
  },
  {
    "no": 33,
    "name": "クリティカルリング",
    "gold": 50000000,
    "effect_id": 0,
    "bonus": {
      "str": 0,
      "int": 0,
      "dex": 0,
      "vit": 0,
      "agi": 0,
      "mnd": 0,
      "lck": 0,
      "lp": 0
    },
    "attrib": 0,
    "spare1": 0,
    "spare2": 30
  },
  {
    "no": 34,
    "name": "戦士の称号",
    "gold": 5000,
    "effect_id": 0,
    "bonus": {
      "str": 10,
      "int": 0,
      "dex": 0,
      "vit": 10,
      "agi": 0,
      "mnd": 0,
      "lck": 0,
      "lp": 0
    },
    "attrib": 0,
    "spare1": 0,
    "spare2": 0
  },
  {
    "no": 35,
    "name": "ナイトの称号",
    "gold": 50000,
    "effect_id": 0,
    "bonus": {
      "str": 25,
      "int": 0,
      "dex": 0,
      "vit": 25,
      "agi": 0,
      "mnd": 0,
      "lck": 0,
      "lp": 0
    },
    "attrib": 0,
    "spare1": 0,
    "spare2": 0
  },
  {
    "no": 36,
    "name": "Ｓｅｅｄ認定証",
    "gold": 750000,
    "effect_id": 0,
    "bonus": {
      "str": 50,
      "int": 0,
      "dex": 0,
      "vit": 50,
      "agi": 0,
      "mnd": 0,
      "lck": 0,
      "lp": 0
    },
    "attrib": 0,
    "spare1": 0,
    "spare2": 0
  },
  {
    "no": 37,
    "name": "魔石",
    "gold": 5000,
    "effect_id": 0,
    "bonus": {
      "str": 0,
      "int": 10,
      "dex": 10,
      "vit": 0,
      "agi": 0,
      "mnd": 0,
      "lck": 0,
      "lp": 0
    },
    "attrib": 0,
    "spare1": 0,
    "spare2": 0
  },
  {
    "no": 38,
    "name": "魔水晶",
    "gold": 50000,
    "effect_id": 0,
    "bonus": {
      "str": 0,
      "int": 25,
      "dex": 25,
      "vit": 0,
      "agi": 0,
      "mnd": 0,
      "lck": 0,
      "lp": 0
    },
    "attrib": 0,
    "spare1": 0,
    "spare2": 0
  },
  {
    "no": 39,
    "name": "魔水晶の指輪",
    "gold": 750000,
    "effect_id": 0,
    "bonus": {
      "str": 0,
      "int": 50,
      "dex": 50,
      "vit": 0,
      "agi": 0,
      "mnd": 0,
      "lck": 0,
      "lp": 0
    },
    "attrib": 0,
    "spare1": 0,
    "spare2": 0
  },
  {
    "no": 40,
    "name": "盗賊の証",
    "gold": 5000,
    "effect_id": 0,
    "bonus": {
      "str": 0,
      "int": 0,
      "dex": 0,
      "vit": 0,
      "agi": 10,
      "mnd": 10,
      "lck": 0,
      "lp": 0
    },
    "attrib": 0,
    "spare1": 0,
    "spare2": 0
  },
  {
    "no": 41,
    "name": "忍者の証",
    "gold": 50000,
    "effect_id": 0,
    "bonus": {
      "str": 0,
      "int": 0,
      "dex": 0,
      "vit": 0,
      "agi": 25,
      "mnd": 25,
      "lck": 0,
      "lp": 0
    },
    "attrib": 0,
    "spare1": 0,
    "spare2": 0
  },
  {
    "no": 42,
    "name": "風間の証",
    "gold": 750000,
    "effect_id": 0,
    "bonus": {
      "str": 0,
      "int": 0,
      "dex": 0,
      "vit": 0,
      "agi": 50,
      "mnd": 50,
      "lck": 0,
      "lp": 0
    },
    "attrib": 0,
    "spare1": 0,
    "spare2": 0
  },
  {
    "no": 43,
    "name": "オールボーナス",
    "gold": 5000,
    "effect_id": 0,
    "bonus": {
      "str": 5,
      "int": 5,
      "dex": 5,
      "vit": 5,
      "agi": 0,
      "mnd": 0,
      "lck": 0,
      "lp": 0
    },
    "attrib": 0,
    "spare1": 0,
    "spare2": 0
  },
  {
    "no": 44,
    "name": "ノルンの輝き",
    "gold": 75000,
    "effect_id": 0,
    "bonus": {
      "str": 10,
      "int": 10,
      "dex": 10,
      "vit": 10,
      "agi": 10,
      "mnd": 10,
      "lck": 0,
      "lp": 0
    },
    "attrib": 0,
    "spare1": 0,
    "spare2": 0
  },
  {
    "no": 45,
    "name": "アルテミスの指輪",
    "gold": 800000,
    "effect_id": 0,
    "bonus": {
      "str": 20,
      "int": 20,
      "dex": 20,
      "vit": 20,
      "agi": 20,
      "mnd": 20,
      "lck": 0,
      "lp": 0
    },
    "attrib": 0,
    "spare1": 0,
    "spare2": 0
  },
  {
    "no": 46,
    "name": "ラクシュミの王冠",
    "gold": 5000000,
    "effect_id": 0,
    "bonus": {
      "str": 50,
      "int": 50,
      "dex": 50,
      "vit": 50,
      "agi": 50,
      "mnd": 50,
      "lck": 0,
      "lp": 0
    },
    "attrib": 0,
    "spare1": 0,
    "spare2": 0
  },
  {
    "no": 47,
    "name": "バッカスの腕輪",
    "gold": 9999999,
    "effect_id": 0,
    "bonus": {
      "str": 100,
      "int": 0,
      "dex": 0,
      "vit": 0,
      "agi": 0,
      "mnd": 0,
      "lck": 0,
      "lp": 100
    },
    "attrib": 0,
    "spare1": 0,
    "spare2": 0
  },
  {
    "no": 48,
    "name": "武神の腕輪",
    "gold": 99999999,
    "effect_id": 0,
    "bonus": {
      "str": 200,
      "int": 0,
      "dex": 0,
      "vit": 0,
      "agi": 0,
      "mnd": 0,
      "lck": 0,
      "lp": 200
    },
    "attrib": 0,
    "spare1": 0,
    "spare2": 0
  },
  {
    "no": 49,
    "name": "シヴァ・ソウル",
    "gold": 1500000000,
    "effect_id": 0,
    "bonus": {
      "str": 500,
      "int": 0,
      "dex": 0,
      "vit": 0,
      "agi": 0,
      "mnd": 0,
      "lck": 0,
      "lp": 500
    },
    "attrib": 0,
    "spare1": 0,
    "spare2": 0
  },
  {
    "no": 50,
    "name": "メテオリング",
    "gold": 9999999,
    "effect_id": 0,
    "bonus": {
      "str": 0,
      "int": 100,
      "dex": 100,
      "vit": 0,
      "agi": 0,
      "mnd": 0,
      "lck": 0,
      "lp": 0
    },
    "attrib": 0,
    "spare1": 0,
    "spare2": 0
  },
  {
    "no": 51,
    "name": "アルテマリング",
    "gold": 99999999,
    "effect_id": 0,
    "bonus": {
      "str": 0,
      "int": 200,
      "dex": 200,
      "vit": 0,
      "agi": 0,
      "mnd": 0,
      "lck": 0,
      "lp": 0
    },
    "attrib": 0,
    "spare1": 0,
    "spare2": 0
  },
  {
    "no": 52,
    "name": "スリースターズ",
    "gold": 1500000000,
    "effect_id": 0,
    "bonus": {
      "str": 0,
      "int": 500,
      "dex": 500,
      "vit": 0,
      "agi": 0,
      "mnd": 0,
      "lck": 0,
      "lp": 0
    },
    "attrib": 0,
    "spare1": 0,
    "spare2": 0
  },
  {
    "no": 53,
    "name": "回復の指輪",
    "gold": 9999999,
    "effect_id": 1,
    "bonus": {
      "str": 0,
      "int": 0,
      "dex": 0,
      "vit": 0,
      "agi": 0,
      "mnd": 0,
      "lck": 0,
      "lp": 0
    },
    "attrib": 0,
    "spare1": 0,
    "spare2": 0
  },
  {
    "no": 54,
    "name": "全快の指輪",
    "gold": 1500000000,
    "effect_id": 2,
    "bonus": {
      "str": 0,
      "int": 0,
      "dex": 0,
      "vit": 0,
      "agi": 0,
      "mnd": 0,
      "lck": 0,
      "lp": 0
    },
    "attrib": 0,
    "spare1": 0,
    "spare2": 0
  },
  {
    "no": 55,
    "name": "無敵の指輪",
    "gold": 6000000000,
    "effect_id": 3,
    "bonus": {
      "str": 0,
      "int": 0,
      "dex": 0,
      "vit": 0,
      "agi": 0,
      "mnd": 0,
      "lck": 0,
      "lp": 0
    },
    "attrib": 0,
    "spare1": 0,
    "spare2": 0
  },
  {
    "no": 56,
    "name": "プロテスリング",
    "gold": 999999,
    "effect_id": 4,
    "bonus": {
      "str": 0,
      "int": 0,
      "dex": 0,
      "vit": 0,
      "agi": 0,
      "mnd": 0,
      "lck": 0,
      "lp": 0
    },
    "attrib": 0,
    "spare1": 0,
    "spare2": 0
  },
  {
    "no": 57,
    "name": "シェルリング",
    "gold": 99999999,
    "effect_id": 5,
    "bonus": {
      "str": 0,
      "int": 0,
      "dex": 0,
      "vit": 0,
      "agi": 0,
      "mnd": 0,
      "lck": 0,
      "lp": 0
    },
    "attrib": 0,
    "spare1": 0,
    "spare2": 0
  },
  {
    "no": 58,
    "name": "ウォールリング",
    "gold": 150000000,
    "effect_id": 6,
    "bonus": {
      "str": 0,
      "int": 0,
      "dex": 0,
      "vit": 0,
      "agi": 0,
      "mnd": 0,
      "lck": 0,
      "lp": 0
    },
    "attrib": 0,
    "spare1": 0,
    "spare2": 0
  },
  {
    "no": 59,
    "name": "バーサクリング",
    "gold": 999999,
    "effect_id": 7,
    "bonus": {
      "str": 0,
      "int": 0,
      "dex": 0,
      "vit": 0,
      "agi": 0,
      "mnd": 0,
      "lck": 0,
      "lp": 0
    },
    "attrib": 0,
    "spare1": 0,
    "spare2": 0
  },
  {
    "no": 60,
    "name": "魔神の指輪",
    "gold": 99999999,
    "effect_id": 8,
    "bonus": {
      "str": 0,
      "int": 0,
      "dex": 0,
      "vit": 0,
      "agi": 0,
      "mnd": 0,
      "lck": 0,
      "lp": 0
    },
    "attrib": 0,
    "spare1": 0,
    "spare2": 0
  },
  {
    "no": 61,
    "name": "鬼神の指輪",
    "gold": 150000000,
    "effect_id": 9,
    "bonus": {
      "str": 0,
      "int": 0,
      "dex": 0,
      "vit": 0,
      "agi": 0,
      "mnd": 0,
      "lck": 0,
      "lp": 0
    },
    "attrib": 0,
    "spare1": 0,
    "spare2": 0
  },
  {
    "no": 62,
    "name": "オーラの結晶",
    "gold": 100000000,
    "effect_id": 10,
    "bonus": {
      "str": 0,
      "int": 0,
      "dex": 0,
      "vit": 0,
      "agi": 0,
      "mnd": 0,
      "lck": 0,
      "lp": 0
    },
    "attrib": 0,
    "spare1": 0,
    "spare2": 0
  },
  {
    "no": 63,
    "name": "ケアルガの結晶",
    "gold": 100000000,
    "effect_id": 11,
    "bonus": {
      "str": 0,
      "int": 0,
      "dex": 0,
      "vit": 0,
      "agi": 0,
      "mnd": 0,
      "lck": 0,
      "lp": 0
    },
    "attrib": 0,
    "spare1": 0,
    "spare2": 0
  },
  {
    "no": 64,
    "name": "光の結晶",
    "gold": 100000000,
    "effect_id": 12,
    "bonus": {
      "str": 0,
      "int": 0,
      "dex": 0,
      "vit": 0,
      "agi": 0,
      "mnd": 0,
      "lck": 0,
      "lp": 0
    },
    "attrib": 0,
    "spare1": 0,
    "spare2": 0
  },
  {
    "no": 65,
    "name": "隕石のかけら",
    "gold": 100000000,
    "effect_id": 13,
    "bonus": {
      "str": 0,
      "int": 0,
      "dex": 0,
      "vit": 0,
      "agi": 0,
      "mnd": 0,
      "lck": 0,
      "lp": 0
    },
    "attrib": 0,
    "spare1": 0,
    "spare2": 0
  },
  {
    "no": 66,
    "name": "波動の結晶",
    "gold": 150000000,
    "effect_id": 14,
    "bonus": {
      "str": 0,
      "int": 0,
      "dex": 0,
      "vit": 0,
      "agi": 0,
      "mnd": 0,
      "lck": 0,
      "lp": 0
    },
    "attrib": 0,
    "spare1": 0,
    "spare2": 0
  },
  {
    "no": 67,
    "name": "異次元の結晶",
    "gold": 250000000,
    "effect_id": 15,
    "bonus": {
      "str": 0,
      "int": 0,
      "dex": 0,
      "vit": 0,
      "agi": 0,
      "mnd": 0,
      "lck": 0,
      "lp": 0
    },
    "attrib": 0,
    "spare1": 0,
    "spare2": 0
  },
  {
    "no": 68,
    "name": "皇帝の杯",
    "gold": 999999999,
    "effect_id": 16,
    "bonus": {
      "str": 50,
      "int": 50,
      "dex": 50,
      "vit": 50,
      "agi": 50,
      "mnd": 50,
      "lck": 0,
      "lp": 0
    },
    "attrib": 0,
    "spare1": 0,
    "spare2": 0
  },
  {
    "no": 69,
    "name": "オメガ・ソウル",
    "gold": 3000000000,
    "effect_id": 17,
    "bonus": {
      "str": 100,
      "int": 100,
      "dex": 100,
      "vit": 100,
      "agi": 100,
      "mnd": 100,
      "lck": 0,
      "lp": 0
    },
    "attrib": 0,
    "spare1": 0,
    "spare2": 0
  },
  {
    "no": 70,
    "name": "銀河の翡翠",
    "gold": 15000000000,
    "effect_id": 18,
    "bonus": {
      "str": 300,
      "int": 300,
      "dex": 300,
      "vit": 300,
      "agi": 300,
      "mnd": 300,
      "lck": 300,
      "lp": 0
    },
    "attrib": 0,
    "spare1": 0,
    "spare2": 0
  },
  {
    "no": 71,
    "name": "封印球",
    "gold": 15000000000,
    "effect_id": 19,
    "bonus": {
      "str": 300,
      "int": 300,
      "dex": 300,
      "vit": 300,
      "agi": 300,
      "mnd": 300,
      "lck": 300,
      "lp": 0
    },
    "attrib": 0,
    "spare1": 0,
    "spare2": 0
  },
  {
    "no": 72,
    "name": "オリハルコンメダル",
    "gold": 15000000000,
    "effect_id": 20,
    "bonus": {
      "str": 300,
      "int": 300,
      "dex": 300,
      "vit": 300,
      "agi": 300,
      "mnd": 300,
      "lck": 300,
      "lp": 0
    },
    "attrib": 0,
    "spare1": 0,
    "spare2": 999
  },
  {
    "no": 73,
    "name": "夢幻のマテリア",
    "gold": 15000000000,
    "effect_id": 21,
    "bonus": {
      "str": 300,
      "int": 300,
      "dex": 300,
      "vit": 300,
      "agi": 300,
      "mnd": 300,
      "lck": 300,
      "lp": 0
    },
    "attrib": 0,
    "spare1": 0,
    "spare2": 0
  },
  {
    "no": 74,
    "name": "古代の水鏡",
    "gold": 15000000000,
    "effect_id": 22,
    "bonus": {
      "str": 300,
      "int": 300,
      "dex": 300,
      "vit": 300,
      "agi": 300,
      "mnd": 300,
      "lck": 300,
      "lp": 0
    },
    "attrib": 0,
    "spare1": 0,
    "spare2": 0
  },
  {
    "no": 75,
    "name": "反魂香",
    "gold": 15000000000,
    "effect_id": 23,
    "bonus": {
      "str": 300,
      "int": 300,
      "dex": 300,
      "vit": 300,
      "agi": 300,
      "mnd": 300,
      "lck": 300,
      "lp": 0
    },
    "attrib": 0,
    "spare1": 0,
    "spare2": 0
  },
  {
    "no": 77,
    "name": "ルナ・ブレスレット",
    "gold": 15000000000,
    "effect_id": 24,
    "bonus": {
      "str": 300,
      "int": 300,
      "dex": 300,
      "vit": 300,
      "agi": 300,
      "mnd": 300,
      "lck": 300,
      "lp": 0
    },
    "attrib": 30,
    "spare1": 30,
    "spare2": 30
  },
  {
    "no": 78,
    "name": "オニオンネックレス",
    "gold": 555000000000,
    "effect_id": 20,
    "bonus": {
      "str": 2000,
      "int": 2000,
      "dex": 2000,
      "vit": 2000,
      "agi": 2000,
      "mnd": 2000,
      "lck": 2000,
      "lp": 0
    },
    "attrib": 30,
    "spare1": 30,
    "spare2": 999
  },
  {
    "no": 79,
    "name": "キル・クラフト",
    "gold": 335000000000,
    "effect_id": 22,
    "bonus": {
      "str": 800,
      "int": 800,
      "dex": 800,
      "vit": 800,
      "agi": 800,
      "mnd": 800,
      "lck": 800,
      "lp": 0
    },
    "attrib": 0,
    "spare1": 0,
    "spare2": 500
  },
  {
    "no": 80,
    "name": "聖書",
    "gold": 655000000000,
    "effect_id": 24,
    "bonus": {
      "str": 3000,
      "int": 3000,
      "dex": 3000,
      "vit": 3000,
      "agi": 3000,
      "mnd": 3000,
      "lck": 3000,
      "lp": 0
    },
    "attrib": 30,
    "spare1": 30,
    "spare2": 300
  },
  {
    "no": 81,
    "name": "ダイダロスの翡翠",
    "gold": 855000000000,
    "effect_id": 24,
    "bonus": {
      "str": 3000,
      "int": 3000,
      "dex": 3000,
      "vit": 3000,
      "agi": 3000,
      "mnd": 3000,
      "lck": 3000,
      "lp": 0
    },
    "attrib": 300,
    "spare1": 300,
    "spare2": 300
  },
  {
    "no": 82,
    "name": "ホーリークロス",
    "gold": 855000000000,
    "effect_id": 24,
    "bonus": {
      "str": 3000,
      "int": 3000,
      "dex": 3000,
      "vit": 3000,
      "agi": 3000,
      "mnd": 3000,
      "lck": 3000,
      "lp": 0
    },
    "attrib": 300,
    "spare1": 300,
    "spare2": 300
  },
  {
    "no": 83,
    "name": "勇者の紋章",
    "gold": 855000000000,
    "effect_id": 23,
    "bonus": {
      "str": 3000,
      "int": 3000,
      "dex": 3000,
      "vit": 3000,
      "agi": 3000,
      "mnd": 3000,
      "lck": 3000,
      "lp": 0
    },
    "attrib": 10,
    "spare1": 10,
    "spare2": 10
  },
  {
    "no": 84,
    "name": "銀河のしずく",
    "gold": 855000000000,
    "effect_id": 24,
    "bonus": {
      "str": 3000,
      "int": 3000,
      "dex": 3000,
      "vit": 3000,
      "agi": 3000,
      "mnd": 3000,
      "lck": 3000,
      "lp": 0
    },
    "attrib": 30,
    "spare1": 30,
    "spare2": 30
  },
  {
    "no": 85,
    "name": "blessings",
    "gold": 999999999999,
    "effect_id": 22,
    "bonus": {
      "str": 3500,
      "int": 3500,
      "dex": 3500,
      "vit": 3500,
      "agi": 3500,
      "mnd": 3500,
      "lck": 3500,
      "lp": 0
    },
    "attrib": 0,
    "spare1": 0,
    "spare2": 0
  },
  {
    "no": 86,
    "name": "クレア・バイブル",
    "gold": 999999999999,
    "effect_id": 23,
    "bonus": {
      "str": 3500,
      "int": 3500,
      "dex": 3500,
      "vit": 3500,
      "agi": 3500,
      "mnd": 3500,
      "lck": 3500,
      "lp": 0
    },
    "attrib": 100,
    "spare1": 100,
    "spare2": 0
  },
  {
    "no": 87,
    "name": "ガイアフォースの結晶",
    "gold": 999999999999,
    "effect_id": 24,
    "bonus": {
      "str": 9999,
      "int": 9999,
      "dex": 9999,
      "vit": 9999,
      "agi": 9999,
      "mnd": 9999,
      "lck": 9999,
      "lp": 0
    },
    "attrib": 0,
    "spare1": 0,
    "spare2": 0
  },
  {
    "no": 999,
    "name": "なし",
    "gold": 0,
    "effect_id": 0,
    "bonus": {
      "str": 0,
      "int": 0,
      "dex": 0,
      "vit": 0,
      "agi": 0,
      "mnd": 0,
      "lck": 0,
      "lp": 0
    },
    "attrib": 0,
    "spare1": 0,
    "spare2": 0
  }
]