[
  {
    "breader": "管理人",
    "name": "ウカラボ",
    "no": 1,
    "type": 3,
    "max": 1450,
    "c0": 103,
    "c1": 295,
    "c2": 72,
    "c3": 40,
    "c4": 309,
    "c5": 296,
    "c6": 339
  },
  {
    "breader": "管理人",
    "name": "クノオ",
    "no": 5,
    "type": 0,
    "max": 1728,
    "c0": 141,
    "c1": 238,
    "c2": 169,
    "c3": 294,
    "c4": 306,
    "c5": 504,
    "c6": 79
  },
  {
    "breader": "管理人",
    "name": "モチャハコ",
    "no": 1,
    "type": 3,
    "max": 1512,
    "c0": 248,
    "c1": 70,
    "c2": 207,
    "c3": 195,
    "c4": 349,
    "c5": 82,
    "c6": 364
  },
  {
    "breader": "管理人",
    "name": "ワレテシ",
    "no": 6,
    "type": 0,
    "max": 2084,
    "c0": 76,
    "c1": 143,
    "c2": 521,
    "c3": 346,
    "c4": 219,
    "c5": 475,
    "c6": 308
  },
  {
    "breader": "管理人",
    "name": "マッタノダケ",
    "no": 2,
    "type": 4,
    "max": 1853,
    "c0": 259,
    "c1": 438,
    "c2": 250,
    "c3": 371,
    "c4": 193,
    "c5": 139,
    "c6": 207
  },
  {
    "breader": "管理人",
    "name": "レドモア",
    "no": 4,
    "type": 4,
    "max": 2038,
    "c0": 208,
    "c1": 45,
    "c2": 225,
    "c3": 532,
    "c4": 324,
    "c5": 407,
    "c6": 301
  },
  {
    "breader": "管理人",
    "name": "シタハハ",
    "no": 5,
    "type": 2,
    "max": 1644,
    "c0": 365,
    "c1": 344,
    "c2": 333,
    "c3": 81,
    "c4": 105,
    "c5": 157,
    "c6": 261
  },
  {
    "breader": "管理人",
    "name": "レルカナク",
    "no": 4,
    "type": 4,
    "max": 1894,
    "c0": 162,
    "c1": 10,
    "c2": 169,
    "c3": 644,
    "c4": 289,
    "c5": 381,
    "c6": 243
  },
  {
    "breader": "管理人",
    "name": "モリハイ",
    "no": 2,
    "type": 0,
    "max": 2032,
    "c0": 177,
    "c1": 349,
    "c2": 365,
    "c3": 206,
    "c4": 308,
    "c5": 329,
    "c6": 301
  },
  {
    "breader": "管理人",
    "name": "ダナワ",
    "no": 0,
    "type": 4,
    "max": 1975,
    "c0": 391,
    "c1": 68,
    "c2": 236,
    "c3": 412,
    "c4": 148,
    "c5": 78,
    "c6": 645
  },
  {
    "breader": "管理人",
    "name": "タシア",
    "no": 4,
    "type": 1,
    "max": 1469,
    "c0": 15,
    "c1": 277,
    "c2": 256,
    "c3": 138,
    "c4": 247,
    "c5": 229,
    "c6": 310
  },
  {
    "breader": "管理人",
    "name": "シタデ",
    "no": 3,
    "type": 0,
    "max": 1451,
    "c0": 257,
    "c1": 69,
    "c2": 323,
    "c3": 120,
    "c4": 22,
    "c5": 412,
    "c6": 251
  },
  {
    "breader": "管理人",
    "name": "エトナ",
    "no": 6,
    "type": 0,
    "max": 1469,
    "c0": 533,
    "c1": 257,
    "c2": 70,
    "c3": 287,
    "c4": 50,
    "c5": 165,
    "c6": 112
  },
  {
    "breader": "管理人",
    "name": "ノニハナ",
    "no": 0,
    "type": 0,
    "max": 1519,
    "c0": 246,
    "c1": 162,
    "c2": 374,
    "c3": 94,
    "c4": 225,
    "c5": 188,
    "c6": 233
  },
  {
    "breader": "管理人",
    "name": "ニキテイ",
    "no": 0,
    "type": 4,
    "max": 2023,
    "c0": 178,
    "c1": 101,
    "c2": 316,
    "c3": 218,
    "c4": 322,
    "c5": 387,
    "c6": 504
  },
  {
    "breader": "管理人",
    "name": "コウカナタ",
    "no": 1,
    "type": 3,
    "max": 1661,
    "c0": 205,
    "c1": 254,
    "c2": 221,
    "c3": 273,
    "c4": 327,
    "c5": 108,
    "c6": 277
  },
  {
    "breader": "管理人",
    "name": "ンボノア",
    "no": 1,
    "type": 1,
    "max": 1617,
    "c0": 351,
    "c1": 146,
    "c2": 332,
    "c3": 267,
    "c4": 111,
    "c5": 323,
    "c6": 89
  },
  {
    "breader": "管理人",
    "name": "ゼミチア",
    "no": 2,
    "type": 2,
    "max": 1904,
    "c0": 135,
    "c1": 417,
    "c2": 241,
    "c3": 500,
    "c4": 82,
    "c5": 201,
    "c6": 333
  },
  {
    "breader": "管理人",
    "name": "ルキニ",
    "no": 4,
    "type": 1,
    "max": 1769,
    "c0": 331,
    "c1": 178,
    "c2": 312,
    "c3": 170,
    "c4": 158,
    "c5": 381,
    "c6": 243
  },
  {
    "breader": "管理人",
    "name": "クインダ",
    "no": 2,
    "type": 4,
    "max": 2062,
    "c0": 152,
    "c1": 504,
    "c2": 285,
    "c3": 268,
    "c4": 453,
    "c5": 369,
    "c6": 35
  },
  {
    "breader": "管理人",
    "name": "ヨネク",
    "no": 1,
    "type": 3,
    "max": 1418,
    "c0": 248,
    "c1": 76,
    "c2": 200,
    "c3": 199,
    "c4": 279,
    "c5": 228,
    "c6": 191
  },
  {
    "breader": "管理人",
    "name": "ルマジャム",
    "no": 6,
    "type": 4,
    "max": 1908,
    "c0": 187,
    "c1": 82,
    "c2": 94,
    "c3": 474,
    "c4": 296,
    "c5": 346,
    "c6": 432
  },
  {
    "breader": "管理人",
    "name": "ズカシイミ",
    "no": 6,
    "type": 4,
    "max": 1401,
    "c0": 206,
    "c1": 234,
    "c2": 29,
    "c3": 175,
    "c4": 182,
    "c5": 236,
    "c6": 342
  },
  {
    "breader": "管理人",
    "name": "チナン",
    "no": 1,
    "type": 3,
    "max": 1961,
    "c0": 207,
    "c1": 347,
    "c2": 447,
    "c3": 122,
    "c4": 108,
    "c5": 232,
    "c6": 502
  },
  {
    "breader": "管理人",
    "name": "ダヨホ",
    "no": 0,
    "type": 4,
    "max": 1960,
    "c0": 344,
    "c1": 292,
    "c2": 140,
    "c3": 157,
    "c4": 516,
    "c5": 218,
    "c6": 296
  },
  {
    "breader": "管理人",
    "name": "テルデト",
    "no": 5,
    "type": 4,
    "max": 1735,
    "c0": 174,
    "c1": 254,
    "c2": 340,
    "c3": 32,
    "c4": 266,
    "c5": 164,
    "c6": 508
  },
  {
    "breader": "管理人",
    "name": "マリタ",
    "no": 5,
    "type": 2,
    "max": 1946,
    "c0": 98,
    "c1": 242,
    "c2": 318,
    "c3": 432,
    "c4": 215,
    "c5": 303,
    "c6": 341
  },
  {
    "breader": "管理人",
    "name": "イエリ",
    "no": 3,
    "type": 2,
    "max": 1857,
    "c0": 145,
    "c1": 23,
    "c2": 31,
    "c3": 359,
    "c4": 181,
    "c5": 624,
    "c6": 497
  },
  {
    "breader": "管理人",
    "name": "トイッショ",
    "no": 6,
    "type": 2,
    "max": 1963,
    "c0": 761,
    "c1": 282,
    "c2": 126,
    "c3": 348,
    "c4": 100,
    "c5": 115,
    "c6": 236
  },
  {
    "breader": "管理人",
    "name": "ニネ",
    "no": 1,
    "type": 0,
    "max": 1704,
    "c0": 779,
    "c1": 144,
    "c2": 168,
    "c3": 350,
    "c4": 10,
    "c5": 240,
    "c6": 15
  },
  {
    "breader": "管理人",
    "name": "タイノセ",
    "no": 4,
    "type": 2,
    "max": 1815,
    "c0": 91,
    "c1": 505,
    "c2": 322,
    "c3": 420,
    "c4": 96,
    "c5": 124,
    "c6": 259
  },
  {
    "breader": "管理人",
    "name": "クスシ",
    "no": 5,
    "type": 3,
    "max": 1614,
    "c0": 370,
    "c1": 262,
    "c2": 30,
    "c3": 476,
    "c4": 133,
    "c5": 297,
    "c6": 50
  },
  {
    "breader": "管理人",
    "name": "タイヨク",
    "no": 0,
    "type": 3,
    "max": 1857,
    "c0": 107,
    "c1": 451,
    "c2": 193,
    "c3": 195,
    "c4": 583,
    "c5": 5,
    "c6": 328
  },
  {
    "breader": "管理人",
    "name": "ニモキ",
    "no": 3,
    "type": 0,
    "max": 1487,
    "c0": 205,
    "c1": 155,
    "c2": 257,
    "c3": 188,
    "c4": 228,
    "c5": 313,
    "c6": 143
  },
  {
    "breader": "管理人",
    "name": "チントシ",
    "no": 0,
    "type": 0,
    "max": 1650,
    "c0": 304,
    "c1": 103,
    "c2": 360,
    "c3": 269,
    "c4": 223,
    "c5": 332,
    "c6": 63
  },
  {
    "breader": "管理人",
    "name": "タイン",
    "no": 2,
    "type": 0,
    "max": 2030,
    "c0": 174,
    "c1": 239,
    "c2": 484,
    "c3": 355,
    "c4": 41,
    "c5": 414,
    "c6": 327
  },
  {
    "breader": "管理人",
    "name": "ウワラ",
    "no": 5,
    "type": 1,
    "max": 1611,
    "c0": 615,
    "c1": 124,
    "c2": 80,
    "c3": 286,
    "c4": 78,
    "c5": 292,
    "c6": 140
  },
  {
    "breader": "管理人",
    "name": "ハマジャ",
    "no": 2,
    "type": 4,
    "max": 1807,
    "c0": 267,
    "c1": 137,
    "c2": 323,
    "c3": 212,
    "c4": 296,
    "c5": 475,
    "c6": 101
  },
  {
    "breader": "管理人",
    "name": "グガ",
    "no": 3,
    "type": 0,
    "max": 1599,
    "c0": 96,
    "c1": 292,
    "c2": 240,
    "c3": 197,
    "c4": 247,
    "c5": 331,
    "c6": 199
  },
  {
    "breader": "管理人",
    "name": "オポロ",
    "no": 1,
    "type": 4,
    "max": 2064,
    "c0": 519,
    "c1": 486,
    "c2": 432,
    "c3": 230,
    "c4": 236,
    "c5": 40,
    "c6": 124
  },
  {
    "breader": "管理人",
    "name": "モゴニ",
    "no": 4,
    "type": 0,
    "max": 1680,
    "c0": 142,
    "c1": 283,
    "c2": 484,
    "c3": 47,
    "c4": 203,
    "c5": 406,
    "c6": 119
  },
  {
    "breader": "管理人",
    "name": "アザダ",
    "no": 3,
    "type": 3,
    "max": 1742,
    "c0": 230,
    "c1": 300,
    "c2": 124,
    "c3": 110,
    "c4": 109,
    "c5": 496,
    "c6": 375
  },
  {
    "breader": "管理人",
    "name": "ギチ",
    "no": 3,
    "type": 1,
    "max": 1962,
    "c0": 299,
    "c1": 178,
    "c2": 350,
    "c3": 480,
    "c4": 270,
    "c5": 148,
    "c6": 240
  },
  {
    "breader": "管理人",
    "name": "グダ",
    "no": 3,
    "type": 2,
    "max": 1862,
    "c0": 4,
    "c1": 409,
    "c2": 26,
    "c3": 407,
    "c4": 354,
    "c5": 262,
    "c6": 402
  },
  {
    "breader": "管理人",
    "name": "ハマザ",
    "no": 2,
    "type": 0,
    "max": 2047,
    "c0": 650,
    "c1": 129,
    "c2": 420,
    "c3": 89,
    "c4": 95,
    "c5": 424,
    "c6": 242
  },
  {
    "breader": "管理人",
    "name": "ザピース",
    "no": 2,
    "type": 2,
    "max": 1949,
    "c0": 440,
    "c1": 382,
    "c2": 218,
    "c3": 343,
    "c4": 120,
    "c5": 130,
    "c6": 320
  },
  {
    "breader": "管理人",
    "name": "ドドンゾ",
    "no": 0,
    "type": 3,
    "max": 1652,
    "c0": 187,
    "c1": 123,
    "c2": 439,
    "c3": 199,
    "c4": 399,
    "c5": 103,
    "c6": 204
  },
  {
    "breader": "管理人",
    "name": "モゾ",
    "no": 2,
    "type": 2,
    "max": 1742,
    "c0": 290,
    "c1": 196,
    "c2": 242,
    "c3": 317,
    "c4": 269,
    "c5": 338,
    "c6": 94
  },
  {
    "breader": "管理人",
    "name": "ゲガキン",
    "no": 5,
    "type": 1,
    "max": 1701,
    "c0": 72,
    "c1": 342,
    "c2": 381,
    "c3": 209,
    "c4": 205,
    "c5": 402,
    "c6": 93
  },
  {
    "breader": "管理人",
    "name": "ザクレス",
    "no": 5,
    "type": 1,
    "max": 2045,
    "c0": 46,
    "c1": 366,
    "c2": 351,
    "c3": 468,
    "c4": 318,
    "c5": 375,
    "c6": 124
  },
  {
    "breader": "管理人",
    "name": "チョコポ",
    "no": 2,
    "type": 2,
    "max": 1904,
    "c0": 436,
    "c1": 21,
    "c2": 217,
    "c3": 650,
    "c4": 365,
    "c5": 102,
    "c6": 117
  }
]